{
  "template": "https://github.com/astroufsc/chimera-template",
  "commit": "0177dff80a2c4e7fcdb67a2f775a1379ba62fb81",
  "checkout": null,
  "context": {
    "cookiecutter": {
      "project_name": "Bisque",
      "project_slug": "chimera-bisque",
      "package_name": "chimera_bisque",
      "__module_name": "bisque",
      "project_short_description": "Chimera plugin for Software Bisque TheSky/TheSkyX telescopes and CCDSoft cameras",
      "author_name": "William Schoenell",
      "author_email": "wschoenell@gmail.com",
      "github_username": "astroufsc",
      "version": "0.1.0",
      "license": "GPL-2.0-or-later",
      "python_version": "3.13",
      "include_instrument": "yes",
      "include_controller": "no",
      "__instrument_class_name": "BisqueInstrument",
      "__controller_class_name": "BisqueController",
      "__instrument_module_name": "bisqueinstrument",
      "__controller_module_name": "bisquecontroller",
      "year": "2026",
      "_template": "https://github.com/astroufsc/chimera-template",
      "_commit": "0177dff80a2c4e7fcdb67a2f775a1379ba62fb81"
    }
  },
  "directory": null
}
